ansys/mapdl/core/__init__.py
ansys/mapdl/core/_version.py
ansys/mapdl/core/commands.py
ansys/mapdl/core/common_grpc.py
ansys/mapdl/core/component.py
ansys/mapdl/core/convert.py
ansys/mapdl/core/errors.py
ansys/mapdl/core/helpers.py
ansys/mapdl/core/information.py
ansys/mapdl/core/jupyter.py
ansys/mapdl/core/krylov.py
ansys/mapdl/core/launcher.py
ansys/mapdl/core/licensing.py
ansys/mapdl/core/logging.py
ansys/mapdl/core/mapdl.py
ansys/mapdl/core/mapdl_console.py
ansys/mapdl/core/mapdl_core.py
ansys/mapdl/core/mapdl_extended.py
ansys/mapdl/core/mapdl_geometry.py
ansys/mapdl/core/mapdl_grpc.py
ansys/mapdl/core/mapdl_inprocess.py
ansys/mapdl/core/mapdl_types.py
ansys/mapdl/core/mesh_grpc.py
ansys/mapdl/core/misc.py
ansys/mapdl/core/parameters.py
ansys/mapdl/core/pool.py
ansys/mapdl/core/post.py
ansys/mapdl/core/report.py
ansys/mapdl/core/solution.py
ansys/mapdl/core/xpl.py
ansys/mapdl/core/_commands/__init__.py
ansys/mapdl/core/_commands/conn.py
ansys/mapdl/core/_commands/hidden.py
ansys/mapdl/core/_commands/inq_func.py
ansys/mapdl/core/_commands/parse.py
ansys/mapdl/core/_commands/apdl/__init__.py
ansys/mapdl/core/_commands/apdl/abbreviations.py
ansys/mapdl/core/_commands/apdl/array_parameters.py
ansys/mapdl/core/_commands/apdl/encryption_decryption.py
ansys/mapdl/core/_commands/apdl/macro_files.py
ansys/mapdl/core/_commands/apdl/matrix_operations.py
ansys/mapdl/core/_commands/apdl/parameter_definition.py
ansys/mapdl/core/_commands/apdl/process_controls.py
ansys/mapdl/core/_commands/aux12/__init__.py
ansys/mapdl/core/_commands/aux12/general_radiation.py
ansys/mapdl/core/_commands/aux12/radiation_matrix_method.py
ansys/mapdl/core/_commands/aux12/radiosity_solver.py
ansys/mapdl/core/_commands/aux15/__init__.py
ansys/mapdl/core/_commands/aux15/iges.py
ansys/mapdl/core/_commands/aux2/__init__.py
ansys/mapdl/core/_commands/aux2/binary_file_dump.py
ansys/mapdl/core/_commands/aux2/binary_file_manipulation.py
ansys/mapdl/core/_commands/aux3/__init__.py
ansys_mapdl_core-0.71.3.dist-info/entry_points.txt
ansys_mapdl_core-0.71.3.dist-info/LICENSE
ansys_mapdl_core-0.71.3.dist-info/WHEEL
ansys_mapdl_core-0.71.3.dist-info/METADATA
ansys_mapdl_core-0.71.3.dist-info/RECORD
