Metadata-Version: 2.3
Name: ansys-mapdl-core
Version: 0.71.3
Summary: A Python client library for Ansys MAPDL.
Author-email: "ANSYS, Inc." <pyansys.core@ansys.com>
Maintainer-email: "ANSYS, Inc." <pyansys.core@ansys.com>
Requires-Python: >=3.10,<3.14
Classifier: Development Status :: 4 - Beta
Classifier: Intended Audience :: Science/Research
Classifier: License :: OSI Approved :: MIT License
Classifier: Operating System :: MacOS
Classifier: Operating System :: Microsoft :: Windows
Classifier: Operating System :: POSIX
Classifier: Programming Language :: Python :: 3.10
Classifier: Programming Language :: Python :: 3.11
Classifier: Programming Language :: Python :: 3.12
Classifier: Programming Language :: Python :: 3.13
Classifier: Topic :: Scientific/Engineering :: Information Analysis
Requires-Dist: ansys-api-mapdl==0.5.2
Requires-Dist: ansys-mapdl-reader>=0.51.7
Requires-Dist: ansys-math-core>=0.1.2
Requires-Dist: ansys-platform-instancemanagement~=1.0
Requires-Dist: ansys-tools-common>=0.2.1
Requires-Dist: click>=8.1.3
Requires-Dist: grpcio>=1.30.0
Requires-Dist: numpy>=1.14.0,<3.0.0
Requires-Dist: pexpect>=4.8.0 ; platform_system=='Linux'
Requires-Dist: platformdirs>=3.6.0
Requires-Dist: protobuf>=3.12.2
Requires-Dist: psutil>=5.9.4
Requires-Dist: pyansys-tools-versioning>=0.3.3
Requires-Dist: pyiges[full]>=0.3.1
Requires-Dist: pyvista<=0.46.4
Requires-Dist: scipy>=1.3.0
Requires-Dist: tabulate>=0.8.0
Requires-Dist: tqdm>=4.45.0
Requires-Dist: vtk>=9.0.0,<9.5.3
Requires-Dist: ansys-tools-visualization-interface>=0.9.0,<0.12.0 ; extra == "all"
Requires-Dist: ipywidgets ; extra == "all"
Requires-Dist: jupyterlab>=3 ; extra == "all"
Requires-Dist: matplotlib>=3.0.0 ; extra == "all"
Requires-Dist: ansys-dpf-core[graphics]==0.13.6 ; extra == "doc"
Requires-Dist: ansys-mapdl-reader==0.55.1 ; extra == "doc"
Requires-Dist: ansys-sphinx-theme==1.6.3 ; extra == "doc"
Requires-Dist: ansys-tools-visualization-interface==0.12.1 ; extra == "doc"
Requires-Dist: grpcio==1.76.0 ; extra == "doc"
Requires-Dist: imageio-ffmpeg==0.6.0 ; extra == "doc"
Requires-Dist: imageio==2.37.2 ; extra == "doc"
Requires-Dist: jupyter==1.1.1 ; extra == "doc"
Requires-Dist: jupyter_sphinx==0.5.3 ; extra == "doc"
Requires-Dist: jupyterlab>=3.2.8 ; extra == "doc"
Requires-Dist: linuxdoc==20240924 ; extra == "doc"
Requires-Dist: matplotlib==3.10.7 ; extra == "doc"
Requires-Dist: nbformat==5.10.4 ; extra == "doc"
Requires-Dist: numpydoc==1.9.0 ; extra == "doc"
Requires-Dist: pandas==2.3.3 ; extra == "doc"
Requires-Dist: plotly==6.5.0 ; extra == "doc"
Requires-Dist: pyiges[full]==0.3.2 ; extra == "doc"
Requires-Dist: pypandoc==1.16.2 ; extra == "doc"
Requires-Dist: pytest-sphinx==0.6.3 ; extra == "doc"
Requires-Dist: pythreejs==2.4.2 ; extra == "doc"
Requires-Dist: sphinx-autobuild==2024.10.3 ; extra == "doc"
Requires-Dist: sphinx-autodoc-typehints==3.1.0 ; extra == "doc"
Requires-Dist: sphinx-copybutton==0.5.2 ; extra == "doc"
Requires-Dist: sphinx-design==0.6.1 ; extra == "doc"
Requires-Dist: sphinx-gallery==0.19.0 ; extra == "doc"
Requires-Dist: sphinx-jinja==2.0.2 ; extra == "doc"
Requires-Dist: sphinx-notfound-page==1.1.0 ; extra == "doc"
Requires-Dist: sphinx==8.2.3 ; extra == "doc"
Requires-Dist: sphinxcontrib-websupport==2.0.0 ; extra == "doc"
Requires-Dist: sphinxemoji==0.3.1 ; extra == "doc"
Requires-Dist: vtk==9.5.2 ; extra == "doc"
Requires-Dist: ansys-tools-visualization-interface>=0.9.0,<0.13.0 ; extra == "graphics"
Requires-Dist: matplotlib>=3.0.0 ; extra == "graphics"
Requires-Dist: ipywidgets ; extra == "jupyter"
Requires-Dist: jupyterlab>=3 ; extra == "jupyter"
Requires-Dist: ansys-dpf-core[graphics]==0.13.6 ; extra == "tests"
Requires-Dist: ansys-tools-visualization-interface==0.12.1 ; extra == "tests"
Requires-Dist: autopep8==2.3.2 ; extra == "tests"
Requires-Dist: matplotlib==3.10.7 ; extra == "tests"
Requires-Dist: pandas==2.3.3 ; extra == "tests"
Requires-Dist: pyansys-tools-report==0.9.0 ; extra == "tests"
Requires-Dist: pyfakefs==5.10.2 ; extra == "tests"
Requires-Dist: pyiges[full]==0.3.2 ; extra == "tests"
Requires-Dist: pytest-cov==7.0.0 ; extra == "tests"
Requires-Dist: pytest-profiling==1.8.1 ; extra == "tests"
Requires-Dist: pytest-pyvista==0.3.1 ; extra == "tests"
Requires-Dist: pytest-random-order==1.2.0 ; extra == "tests"
Requires-Dist: pytest-reportlog==1.0.0 ; extra == "tests"
Requires-Dist: pytest-rerunfailures==16.1 ; extra == "tests"
Requires-Dist: pytest-timeout==2.4.0 ; extra == "tests"
Requires-Dist: pytest==9.0.1 ; extra == "tests"
Requires-Dist: scipy==1.15.3 ; extra == "tests"
Requires-Dist: vtk==9.5.2 ; extra == "tests"
Project-URL: Documentation, https://mapdl.docs.pyansys.com
Project-URL: Issues, https://github.com/ansys/pymapdl/issues
Project-URL: Source, https://github.com/ansys/pymapdl
Project-URL: Tracker, https://github.com/ansys/pymapdl/issues
Provides-Extra: all
Provides-Extra: doc
Provides-Extra: graphics
Provides-Extra: jupyter
Provides-Extra: tests
